{
  "antiPatterns": [],
  "complexity": [
    {
      "cyclomatic": 3,
      "symbolId": "src/adapters/storage/sqlite-storage-adapter.ts::SqliteStorageAdapter.init::method"
    },
    {
      "cyclomatic": 3,
      "symbolId": "src/adapters/storage/sqlite-storage-adapter.ts::SqliteStorageAdapter.initEmpty::method"
    },
    {
      "cyclomatic": 2,
      "symbolId": "src/adapters/storage/sqlite-storage-adapter.ts::SqliteStorageAdapter.getDb::method"
    },
    {
      "cyclomatic": 1,
      "symbolId": "src/adapters/storage/sqlite-storage-adapter.ts::SqliteStorageAdapter.database::method"
    },
    {
      "cyclomatic": 5,
      "symbolId": "src/adapters/storage/sqlite-storage-adapter.ts::SqliteStorageAdapter.verifyIntegrity::method"
    },
    {
      "cyclomatic": 1,
      "symbolId": "src/adapters/storage/sqlite-storage-adapter.ts::SqliteStorageAdapter.createTables::method"
    },
    {
      "cyclomatic": 1,
      "symbolId": "src/adapters/storage/sqlite-storage-adapter.ts::SqliteStorageAdapter.clearIndexTables::method"
    },
    {
      "cyclomatic": 2,
      "symbolId": "src/adapters/storage/sqlite-storage-adapter.ts::SqliteStorageAdapter.rebuildFromJson::method"
    },
    {
      "cyclomatic": 4,
      "symbolId": "src/adapters/storage/sqlite-storage-adapter.ts::SqliteStorageAdapter.writeSymbolFile::method"
    },
    {
      "cyclomatic": 3,
      "symbolId": "src/adapters/storage/sqlite-storage-adapter.ts::SqliteStorageAdapter.readSymbolFile::method"
    },
    {
      "cyclomatic": 2,
      "symbolId": "src/adapters/storage/sqlite-storage-adapter.ts::SqliteStorageAdapter.listIndexedFiles::method"
    },
    {
      "cyclomatic": 1,
      "symbolId": "src/adapters/storage/sqlite-storage-adapter.ts::SqliteStorageAdapter.deleteSymbolFile::method"
    },
    {
      "cyclomatic": 3,
      "symbolId": "src/adapters/storage/sqlite-storage-adapter.ts::SqliteStorageAdapter.getSymbolById::method"
    },
    {
      "cyclomatic": 2,
      "symbolId": "src/adapters/storage/sqlite-storage-adapter.ts::SqliteStorageAdapter.getEdgesFrom::method"
    },
    {
      "cyclomatic": 2,
      "symbolId": "src/adapters/storage/sqlite-storage-adapter.ts::SqliteStorageAdapter.getEdgesTo::method"
    },
    {
      "cyclomatic": 2,
      "symbolId": "src/adapters/storage/sqlite-storage-adapter.ts::SqliteStorageAdapter.getAllSymbols::method"
    },
    {
      "cyclomatic": 2,
      "symbolId": "src/adapters/storage/sqlite-storage-adapter.ts::SqliteStorageAdapter.getAllEdges::method"
    },
    {
      "cyclomatic": 5,
      "symbolId": "src/adapters/storage/sqlite-storage-adapter.ts::SqliteStorageAdapter.bulkWrite::method"
    },
    {
      "cyclomatic": 1,
      "symbolId": "src/adapters/storage/sqlite-storage-adapter.ts::SqliteStorageAdapter.persist::method"
    },
    {
      "cyclomatic": 2,
      "symbolId": "src/adapters/storage/sqlite-storage-adapter.ts::SqliteStorageAdapter.close::method"
    },
    {
      "cyclomatic": 2,
      "symbolId": "src/adapters/storage/sqlite-storage-adapter.ts::SqliteStorageAdapter.persistIfNeeded::method"
    },
    {
      "cyclomatic": 3,
      "symbolId": "src/adapters/storage/sqlite-storage-adapter.ts::SqliteStorageAdapter.deleteFileData::method"
    },
    {
      "cyclomatic": 2,
      "symbolId": "src/adapters/storage/sqlite-storage-adapter.ts::SqliteStorageAdapter.getSymbolsForFile::method"
    },
    {
      "cyclomatic": 2,
      "symbolId": "src/adapters/storage/sqlite-storage-adapter.ts::SqliteStorageAdapter.getEdgesForFile::method"
    }
  ],
  "contentHash": "d39b5744b53db164ec04a60a14d2a336619d477fbd93fa4964783f3e9fb13177",
  "edges": [
    {
      "from": "src/adapters/storage/sqlite-storage-adapter.ts::SqliteStorageAdapter::class",
      "kind": "imports",
      "to": "src/core/types.ts::FileIndex::type",
      "typeOnly": true
    },
    {
      "from": "src/adapters/storage/sqlite-storage-adapter.ts::SqliteStorageAdapter::class",
      "kind": "imports",
      "to": "src/core/types.ts::GraphEdge::type",
      "typeOnly": true
    },
    {
      "from": "src/adapters/storage/sqlite-storage-adapter.ts::SqliteStorageAdapter::class",
      "kind": "imports",
      "to": "src/core/types.ts::SymbolNode::type",
      "typeOnly": true
    },
    {
      "from": "src/adapters/storage/sqlite-storage-adapter.ts::SqliteStorageAdapter::class",
      "kind": "imports",
      "to": "src/ports/i-storage-port.ts::IStoragePort::interface",
      "typeOnly": true
    },
    {
      "from": "src/adapters/storage/sqlite-storage-adapter.ts::SqliteStorageAdapter::class",
      "kind": "imports",
      "to": "src/adapters/storage/json-index-reader.ts::JsonIndexReader::class"
    },
    {
      "from": "src/adapters/storage/sqlite-storage-adapter.ts::SqliteStorageAdapter::class",
      "kind": "imports",
      "to": "src/core/logger.ts::createLogger::function"
    },
    {
      "from": "src/adapters/storage/sqlite-storage-adapter.ts::SqliteStorageAdapter::class",
      "kind": "implements",
      "to": "src/ports/i-storage-port.ts::IStoragePort::interface"
    },
    {
      "from": "src/adapters/storage/sqlite-storage-adapter.ts::SqliteStorageAdapter.init::method",
      "kind": "calls",
      "to": "src/adapters/storage/sqlite-storage-adapter.ts::SqliteStorageAdapter.verifyIntegrity::method"
    },
    {
      "from": "src/adapters/storage/sqlite-storage-adapter.ts::SqliteStorageAdapter.init::method",
      "kind": "calls",
      "to": "src/adapters/storage/sqlite-storage-adapter.ts::SqliteStorageAdapter.createTables::method"
    },
    {
      "from": "src/adapters/storage/sqlite-storage-adapter.ts::SqliteStorageAdapter.init::method",
      "kind": "calls",
      "to": "src/adapters/storage/sqlite-storage-adapter.ts::SqliteStorageAdapter.createTables::method"
    },
    {
      "from": "src/adapters/storage/sqlite-storage-adapter.ts::SqliteStorageAdapter.init::method",
      "kind": "calls",
      "to": "src/adapters/storage/sqlite-storage-adapter.ts::SqliteStorageAdapter.rebuildFromJson::method"
    },
    {
      "from": "src/adapters/storage/sqlite-storage-adapter.ts::SqliteStorageAdapter.initEmpty::method",
      "kind": "calls",
      "to": "src/adapters/storage/sqlite-storage-adapter.ts::SqliteStorageAdapter.createTables::method"
    },
    {
      "from": "src/adapters/storage/sqlite-storage-adapter.ts::SqliteStorageAdapter.initEmpty::method",
      "kind": "calls",
      "to": "src/adapters/storage/sqlite-storage-adapter.ts::SqliteStorageAdapter.clearIndexTables::method"
    },
    {
      "from": "src/adapters/storage/sqlite-storage-adapter.ts::SqliteStorageAdapter.database::method",
      "kind": "calls",
      "to": "src/adapters/storage/sqlite-storage-adapter.ts::SqliteStorageAdapter.getDb::method"
    },
    {
      "from": "src/adapters/storage/sqlite-storage-adapter.ts::SqliteStorageAdapter.verifyIntegrity::method",
      "kind": "calls",
      "to": "src/adapters/storage/sqlite-storage-adapter.ts::SqliteStorageAdapter.database::method"
    },
    {
      "from": "src/adapters/storage/sqlite-storage-adapter.ts::SqliteStorageAdapter.createTables::method",
      "kind": "calls",
      "to": "src/adapters/storage/sqlite-storage-adapter.ts::SqliteStorageAdapter.database::method"
    },
    {
      "from": "src/adapters/storage/sqlite-storage-adapter.ts::SqliteStorageAdapter.clearIndexTables::method",
      "kind": "calls",
      "to": "src/adapters/storage/sqlite-storage-adapter.ts::SqliteStorageAdapter.database::method"
    },
    {
      "from": "src/adapters/storage/sqlite-storage-adapter.ts::SqliteStorageAdapter.rebuildFromJson::method",
      "kind": "calls",
      "to": "src/adapters/storage/sqlite-storage-adapter.ts::SqliteStorageAdapter.bulkWrite::method"
    },
    {
      "from": "src/adapters/storage/sqlite-storage-adapter.ts::SqliteStorageAdapter.rebuildFromJson::method",
      "kind": "calls",
      "to": "src/adapters/storage/json-index-reader.ts::JsonIndexReader::class"
    },
    {
      "from": "src/adapters/storage/sqlite-storage-adapter.ts::SqliteStorageAdapter.writeSymbolFile::method",
      "kind": "calls",
      "to": "src/adapters/storage/sqlite-storage-adapter.ts::SqliteStorageAdapter.database::method"
    },
    {
      "from": "src/adapters/storage/sqlite-storage-adapter.ts::SqliteStorageAdapter.writeSymbolFile::method",
      "kind": "calls",
      "to": "src/adapters/storage/sqlite-storage-adapter.ts::SqliteStorageAdapter.deleteFileData::method"
    },
    {
      "from": "src/adapters/storage/sqlite-storage-adapter.ts::SqliteStorageAdapter.writeSymbolFile::method",
      "kind": "calls",
      "to": "src/adapters/storage/sqlite-storage-adapter.ts::SqliteStorageAdapter.persistIfNeeded::method"
    },
    {
      "from": "src/adapters/storage/sqlite-storage-adapter.ts::SqliteStorageAdapter.readSymbolFile::method",
      "kind": "calls",
      "to": "src/adapters/storage/sqlite-storage-adapter.ts::SqliteStorageAdapter.database::method"
    },
    {
      "from": "src/adapters/storage/sqlite-storage-adapter.ts::SqliteStorageAdapter.readSymbolFile::method",
      "kind": "calls",
      "to": "src/adapters/storage/sqlite-storage-adapter.ts::SqliteStorageAdapter.getSymbolsForFile::method"
    },
    {
      "from": "src/adapters/storage/sqlite-storage-adapter.ts::SqliteStorageAdapter.readSymbolFile::method",
      "kind": "calls",
      "to": "src/adapters/storage/sqlite-storage-adapter.ts::SqliteStorageAdapter.getEdgesForFile::method"
    },
    {
      "from": "src/adapters/storage/sqlite-storage-adapter.ts::SqliteStorageAdapter.listIndexedFiles::method",
      "kind": "calls",
      "to": "src/adapters/storage/sqlite-storage-adapter.ts::SqliteStorageAdapter.database::method"
    },
    {
      "from": "src/adapters/storage/sqlite-storage-adapter.ts::SqliteStorageAdapter.deleteSymbolFile::method",
      "kind": "calls",
      "to": "src/adapters/storage/sqlite-storage-adapter.ts::SqliteStorageAdapter.database::method"
    },
    {
      "from": "src/adapters/storage/sqlite-storage-adapter.ts::SqliteStorageAdapter.deleteSymbolFile::method",
      "kind": "calls",
      "to": "src/adapters/storage/sqlite-storage-adapter.ts::SqliteStorageAdapter.deleteFileData::method"
    },
    {
      "from": "src/adapters/storage/sqlite-storage-adapter.ts::SqliteStorageAdapter.getSymbolById::method",
      "kind": "calls",
      "to": "src/adapters/storage/sqlite-storage-adapter.ts::SqliteStorageAdapter.database::method"
    },
    {
      "from": "src/adapters/storage/sqlite-storage-adapter.ts::SqliteStorageAdapter.getEdgesFrom::method",
      "kind": "calls",
      "to": "src/adapters/storage/sqlite-storage-adapter.ts::SqliteStorageAdapter.database::method"
    },
    {
      "from": "src/adapters/storage/sqlite-storage-adapter.ts::SqliteStorageAdapter.getEdgesTo::method",
      "kind": "calls",
      "to": "src/adapters/storage/sqlite-storage-adapter.ts::SqliteStorageAdapter.database::method"
    },
    {
      "from": "src/adapters/storage/sqlite-storage-adapter.ts::SqliteStorageAdapter.getAllSymbols::method",
      "kind": "calls",
      "to": "src/adapters/storage/sqlite-storage-adapter.ts::SqliteStorageAdapter.database::method"
    },
    {
      "from": "src/adapters/storage/sqlite-storage-adapter.ts::SqliteStorageAdapter.getAllEdges::method",
      "kind": "calls",
      "to": "src/adapters/storage/sqlite-storage-adapter.ts::SqliteStorageAdapter.database::method"
    },
    {
      "from": "src/adapters/storage/sqlite-storage-adapter.ts::SqliteStorageAdapter.bulkWrite::method",
      "kind": "calls",
      "to": "src/adapters/storage/sqlite-storage-adapter.ts::SqliteStorageAdapter.database::method"
    },
    {
      "from": "src/adapters/storage/sqlite-storage-adapter.ts::SqliteStorageAdapter.bulkWrite::method",
      "kind": "calls",
      "to": "src/adapters/storage/sqlite-storage-adapter.ts::SqliteStorageAdapter.deleteFileData::method"
    },
    {
      "from": "src/adapters/storage/sqlite-storage-adapter.ts::SqliteStorageAdapter.bulkWrite::method",
      "kind": "calls",
      "to": "src/adapters/storage/sqlite-storage-adapter.ts::SqliteStorageAdapter.persistIfNeeded::method"
    },
    {
      "from": "src/adapters/storage/sqlite-storage-adapter.ts::SqliteStorageAdapter.persist::method",
      "kind": "calls",
      "to": "src/adapters/storage/sqlite-storage-adapter.ts::SqliteStorageAdapter.database::method"
    },
    {
      "from": "src/adapters/storage/sqlite-storage-adapter.ts::SqliteStorageAdapter.close::method",
      "kind": "calls",
      "to": "src/adapters/storage/sqlite-storage-adapter.ts::SqliteStorageAdapter.persist::method"
    },
    {
      "from": "src/adapters/storage/sqlite-storage-adapter.ts::SqliteStorageAdapter.persistIfNeeded::method",
      "kind": "calls",
      "to": "src/adapters/storage/sqlite-storage-adapter.ts::SqliteStorageAdapter.persist::method"
    },
    {
      "from": "src/adapters/storage/sqlite-storage-adapter.ts::SqliteStorageAdapter::class",
      "kind": "uses",
      "to": "src/ports/i-storage-port.ts::IStoragePort::interface"
    },
    {
      "from": "src/adapters/storage/sqlite-storage-adapter.ts::SqliteStorageAdapter::class",
      "kind": "uses",
      "to": "src/adapters/storage/json-index-reader.ts::JsonIndexReader::class"
    },
    {
      "from": "src/adapters/storage/sqlite-storage-adapter.ts::SqliteStorageAdapter::class",
      "kind": "uses",
      "to": "src/core/types.ts::FileIndex::type"
    },
    {
      "from": "src/adapters/storage/sqlite-storage-adapter.ts::SqliteStorageAdapter::class",
      "kind": "uses",
      "to": "src/core/types.ts::SymbolNode::type"
    },
    {
      "from": "src/adapters/storage/sqlite-storage-adapter.ts::SqliteStorageAdapter::class",
      "kind": "uses",
      "to": "src/core/types.ts::GraphEdge::type"
    }
  ],
  "file": "src/adapters/storage/sqlite-storage-adapter.ts",
  "intent": [
    {
      "date": "2026-04-10T04:05:00+03:00",
      "hash": "029c8653121c48ae59932583bde81578756ae684",
      "kind": "commit",
      "message": "fix(stats): persist session events to disk and preserve across index rebuilds"
    },
    {
      "date": "2026-04-10T03:52:10+03:00",
      "hash": "0cf2ae6801b0a02ce046f2587853f888b89b4360",
      "kind": "commit",
      "message": "feat(stats): add ctxo stats command with session recording"
    },
    {
      "date": "2026-04-08T19:15:40+03:00",
      "hash": "d3a80b889a1610d6201e52ab46f6a8672161b3cc",
      "kind": "commit",
      "message": "Fix C# method overload crash causing UNIQUE constraint failure"
    },
    {
      "date": "2026-04-08T17:56:58+03:00",
      "hash": "18430d5cc2948dcaec9c139aaf48686023053b3a",
      "kind": "commit",
      "message": "Add debug mode (DEBUG=ctxo:*), structured logger, and CHANGELOG.md"
    },
    {
      "date": "2026-03-31T02:26:20+03:00",
      "hash": "88dcc914d2f67c3ee240451419f8ab50e2c9abda",
      "kind": "commit",
      "message": "Add cascading dead code, framework awareness, scaffolding detection"
    },
    {
      "date": "2026-03-31T00:18:59+03:00",
      "hash": "2e1bb318ad907f1a22ed0c748489cc44690767fc",
      "kind": "commit",
      "message": "Update index and runbook after context assembly + reindex"
    },
    {
      "date": "2026-03-29T23:00:48+03:00",
      "hash": "25a19286036cb2f61ce9939556de29f472de5406",
      "kind": "commit",
      "message": "Document SQLite data boundary in readSymbolFile"
    },
    {
      "date": "2026-03-29T19:22:39+03:00",
      "hash": "c7389f822bc7c290fca4709cb71fb6beb9011a2e",
      "kind": "commit",
      "message": "Remove FK constraints from edges table — zero edge loss"
    },
    {
      "date": "2026-03-29T19:16:28+03:00",
      "hash": "d496a4d99452fd8c91660a64f26927d5a23a9885",
      "kind": "commit",
      "message": "Fix empty edges in MCP tools: resolve symbol IDs before SQLite insert"
    },
    {
      "date": "2026-03-29T18:40:27+03:00",
      "hash": "8f6be2d264ea742495afd6783ac22f6fd06e6945",
      "kind": "commit",
      "message": "Fix both V1 blockers: TypeScript strict mode and test coverage gate"
    },
    {
      "date": "2026-03-29T16:52:30+03:00",
      "hash": "d8f2f5cae3da8d4749427961bfbd9983cf18da22",
      "kind": "commit",
      "message": "Restore to_symbol FK with graceful error handling for cross-file edges"
    },
    {
      "date": "2026-03-29T16:49:13+03:00",
      "hash": "3d2a69146903edf71a1a4e6797c8f392620ba4b7",
      "kind": "commit",
      "message": "Fix 7 runtime bugs from second code review"
    },
    {
      "date": "2026-03-29T16:17:42+03:00",
      "hash": "7b96d982fdf4c6fd753beeb4129181f9ad91ddb8",
      "kind": "commit",
      "message": "Fix 10 runtime bugs found in code review"
    },
    {
      "date": "2026-03-29T15:50:38+03:00",
      "hash": "a55ee9addcea4a1b3da5a93e6acb2b979c5fb5c8",
      "kind": "commit",
      "message": "Add storage foundation: IStoragePort, JSON index writer/reader, SQLite adapter"
    }
  ],
  "lastModified": 1776014229,
  "symbols": [
    {
      "endLine": 386,
      "endOffset": 11671,
      "kind": "class",
      "name": "SqliteStorageAdapter",
      "startLine": 10,
      "startOffset": 481,
      "symbolId": "src/adapters/storage/sqlite-storage-adapter.ts::SqliteStorageAdapter::class"
    },
    {
      "endLine": 40,
      "endOffset": 1382,
      "kind": "method",
      "name": "SqliteStorageAdapter.init",
      "startLine": 20,
      "startOffset": 789,
      "symbolId": "src/adapters/storage/sqlite-storage-adapter.ts::SqliteStorageAdapter.init::method"
    },
    {
      "endLine": 56,
      "endOffset": 1787,
      "kind": "method",
      "name": "SqliteStorageAdapter.initEmpty",
      "startLine": 42,
      "startOffset": 1388,
      "symbolId": "src/adapters/storage/sqlite-storage-adapter.ts::SqliteStorageAdapter.initEmpty::method"
    },
    {
      "endLine": 64,
      "endOffset": 2036,
      "kind": "method",
      "name": "SqliteStorageAdapter.getDb",
      "startLine": 59,
      "startOffset": 1879,
      "symbolId": "src/adapters/storage/sqlite-storage-adapter.ts::SqliteStorageAdapter.getDb::method"
    },
    {
      "endLine": 68,
      "endOffset": 2103,
      "kind": "method",
      "name": "SqliteStorageAdapter.database",
      "startLine": 66,
      "startOffset": 2042,
      "symbolId": "src/adapters/storage/sqlite-storage-adapter.ts::SqliteStorageAdapter.database::method"
    },
    {
      "endLine": 84,
      "endOffset": 2642,
      "kind": "method",
      "name": "SqliteStorageAdapter.verifyIntegrity",
      "startLine": 70,
      "startOffset": 2109,
      "symbolId": "src/adapters/storage/sqlite-storage-adapter.ts::SqliteStorageAdapter.verifyIntegrity::method"
    },
    {
      "endLine": 115,
      "endOffset": 3602,
      "kind": "method",
      "name": "SqliteStorageAdapter.createTables",
      "startLine": 86,
      "startOffset": 2648,
      "symbolId": "src/adapters/storage/sqlite-storage-adapter.ts::SqliteStorageAdapter.createTables::method"
    },
    {
      "endLine": 122,
      "endOffset": 3784,
      "kind": "method",
      "name": "SqliteStorageAdapter.clearIndexTables",
      "startLine": 117,
      "startOffset": 3608,
      "symbolId": "src/adapters/storage/sqlite-storage-adapter.ts::SqliteStorageAdapter.clearIndexTables::method"
    },
    {
      "endLine": 131,
      "endOffset": 3995,
      "kind": "method",
      "name": "SqliteStorageAdapter.rebuildFromJson",
      "startLine": 124,
      "startOffset": 3790,
      "symbolId": "src/adapters/storage/sqlite-storage-adapter.ts::SqliteStorageAdapter.rebuildFromJson::method"
    },
    {
      "endLine": 165,
      "endOffset": 4973,
      "kind": "method",
      "name": "SqliteStorageAdapter.writeSymbolFile",
      "startLine": 133,
      "startOffset": 4001,
      "symbolId": "src/adapters/storage/sqlite-storage-adapter.ts::SqliteStorageAdapter.writeSymbolFile::method"
    },
    {
      "endLine": 198,
      "endOffset": 5976,
      "kind": "method",
      "name": "SqliteStorageAdapter.readSymbolFile",
      "startLine": 173,
      "startOffset": 5229,
      "symbolId": "src/adapters/storage/sqlite-storage-adapter.ts::SqliteStorageAdapter.readSymbolFile::method"
    },
    {
      "endLine": 205,
      "endOffset": 6222,
      "kind": "method",
      "name": "SqliteStorageAdapter.listIndexedFiles",
      "startLine": 200,
      "startOffset": 5982,
      "symbolId": "src/adapters/storage/sqlite-storage-adapter.ts::SqliteStorageAdapter.listIndexedFiles::method"
    },
    {
      "endLine": 210,
      "endOffset": 6356,
      "kind": "method",
      "name": "SqliteStorageAdapter.deleteSymbolFile",
      "startLine": 207,
      "startOffset": 6228,
      "symbolId": "src/adapters/storage/sqlite-storage-adapter.ts::SqliteStorageAdapter.deleteSymbolFile::method"
    },
    {
      "endLine": 224,
      "endOffset": 6904,
      "kind": "method",
      "name": "SqliteStorageAdapter.getSymbolById",
      "startLine": 212,
      "startOffset": 6362,
      "symbolId": "src/adapters/storage/sqlite-storage-adapter.ts::SqliteStorageAdapter.getSymbolById::method"
    },
    {
      "endLine": 238,
      "endOffset": 7317,
      "kind": "method",
      "name": "SqliteStorageAdapter.getEdgesFrom",
      "startLine": 226,
      "startOffset": 6910,
      "symbolId": "src/adapters/storage/sqlite-storage-adapter.ts::SqliteStorageAdapter.getEdgesFrom::method"
    },
    {
      "endLine": 252,
      "endOffset": 7726,
      "kind": "method",
      "name": "SqliteStorageAdapter.getEdgesTo",
      "startLine": 240,
      "startOffset": 7323,
      "symbolId": "src/adapters/storage/sqlite-storage-adapter.ts::SqliteStorageAdapter.getEdgesTo::method"
    },
    {
      "endLine": 267,
      "endOffset": 8178,
      "kind": "method",
      "name": "SqliteStorageAdapter.getAllSymbols",
      "startLine": 254,
      "startOffset": 7732,
      "symbolId": "src/adapters/storage/sqlite-storage-adapter.ts::SqliteStorageAdapter.getAllSymbols::method"
    },
    {
      "endLine": 280,
      "endOffset": 8533,
      "kind": "method",
      "name": "SqliteStorageAdapter.getAllEdges",
      "startLine": 269,
      "startOffset": 8184,
      "symbolId": "src/adapters/storage/sqlite-storage-adapter.ts::SqliteStorageAdapter.getAllEdges::method"
    },
    {
      "endLine": 316,
      "endOffset": 9590,
      "kind": "method",
      "name": "SqliteStorageAdapter.bulkWrite",
      "startLine": 282,
      "startOffset": 8539,
      "symbolId": "src/adapters/storage/sqlite-storage-adapter.ts::SqliteStorageAdapter.bulkWrite::method"
    },
    {
      "endLine": 324,
      "endOffset": 9821,
      "kind": "method",
      "name": "SqliteStorageAdapter.persist",
      "startLine": 318,
      "startOffset": 9596,
      "symbolId": "src/adapters/storage/sqlite-storage-adapter.ts::SqliteStorageAdapter.persist::method"
    },
    {
      "endLine": 332,
      "endOffset": 9949,
      "kind": "method",
      "name": "SqliteStorageAdapter.close",
      "startLine": 326,
      "startOffset": 9827,
      "symbolId": "src/adapters/storage/sqlite-storage-adapter.ts::SqliteStorageAdapter.close::method"
    },
    {
      "endLine": 340,
      "endOffset": 10124,
      "kind": "method",
      "name": "SqliteStorageAdapter.persistIfNeeded",
      "startLine": 334,
      "startOffset": 9955,
      "symbolId": "src/adapters/storage/sqlite-storage-adapter.ts::SqliteStorageAdapter.persistIfNeeded::method"
    },
    {
      "endLine": 355,
      "endOffset": 10667,
      "kind": "method",
      "name": "SqliteStorageAdapter.deleteFileData",
      "startLine": 342,
      "startOffset": 10130,
      "symbolId": "src/adapters/storage/sqlite-storage-adapter.ts::SqliteStorageAdapter.deleteFileData::method"
    },
    {
      "endLine": 370,
      "endOffset": 11187,
      "kind": "method",
      "name": "SqliteStorageAdapter.getSymbolsForFile",
      "startLine": 357,
      "startOffset": 10673,
      "symbolId": "src/adapters/storage/sqlite-storage-adapter.ts::SqliteStorageAdapter.getSymbolsForFile::method"
    },
    {
      "endLine": 385,
      "endOffset": 11668,
      "kind": "method",
      "name": "SqliteStorageAdapter.getEdgesForFile",
      "startLine": 372,
      "startOffset": 11193,
      "symbolId": "src/adapters/storage/sqlite-storage-adapter.ts::SqliteStorageAdapter.getEdgesForFile::method"
    }
  ]
}